pyonvista/__init__.py
pyonvista/api.py
pyonvista/util.py
pyonvista_v2-2.0.2.dist-info/licenses/LICENSE.md
pyonvista_v2-2.0.2.dist-info/METADATA
pyonvista_v2-2.0.2.dist-info/WHEEL
pyonvista_v2-2.0.2.dist-info/top_level.txt
pyonvista_v2-2.0.2.dist-info/RECORD
