Metadata-Version: 2.4
Name: pyonvista-v2
Version: 2.0.2
Summary: Enhanced Python API for OnVista financial data with comprehensive fundamental analysis capabilities
Author-email: Simon Bauer <seimen@cloasdata.de>, Jan Philipp Tebbe <info@thukyd.com>
Maintainer-email: Jan Philipp Tebbe <info@thukyd.com>
License-Expression: MIT
Project-URL: Homepage, https://github.com/Thukyd/pyOnvista
Project-URL: Repository, https://github.com/Thukyd/pyOnvista
Project-URL: Documentation, https://github.com/Thukyd/pyOnvista#readme
Project-URL: Bug Tracker, https://github.com/Thukyd/pyOnvista/issues
Project-URL: Changelog, https://github.com/Thukyd/pyOnvista/releases
Keywords: finance,stocks,financial-data,onvista,german-stocks,fundamental-analysis,esg,financial-ratios,stock-analysis,investment,trading,market-data
Classifier: Development Status :: 5 - Production/Stable
Classifier: Intended Audience :: Developers
Classifier: Intended Audience :: Financial and Insurance Industry
Classifier: Operating System :: OS Independent
Classifier: Programming Language :: Python :: 3
Classifier: Programming Language :: Python :: 3.8
Classifier: Programming Language :: Python :: 3.9
Classifier: Programming Language :: Python :: 3.10
Classifier: Programming Language :: Python :: 3.11
Classifier: Programming Language :: Python :: 3.12
Classifier: Topic :: Office/Business :: Financial
Classifier: Topic :: Office/Business :: Financial :: Investment
Classifier: Topic :: Software Development :: Libraries :: Python Modules
Classifier: Typing :: Typed
Requires-Python: >=3.8
License-File: LICENSE.md
Requires-Dist: aiohttp>=3.8.1
Provides-Extra: test
Requires-Dist: pytest>=7.0.0; extra == "test"
Requires-Dist: pytest-asyncio>=0.21.0; extra == "test"
Provides-Extra: dev
Requires-Dist: pytest>=7.0.0; extra == "dev"
Requires-Dist: pytest-asyncio>=0.21.0; extra == "dev"
Requires-Dist: black; extra == "dev"
Requires-Dist: isort; extra == "dev"
Requires-Dist: mypy; extra == "dev"
Dynamic: license-file
